xian_cli/__init__.py
xian_cli/constants.py
xian_cli/main.py
xian_cli/utils.py
xian_cli-0.1.0.dist-info/METADATA
xian_cli-0.1.0.dist-info/WHEEL
xian_cli-0.1.0.dist-info/entry_points.txt
xian_cli-0.1.0.dist-info/RECORD
