Metadata-Version: 2.1
Name: xian-cli
Version: 0.1.0
Summary: 
Author: Revolutionnnn
Author-email: ganandocriptomonedass@gmail.com
Requires-Python: >=3.12,<4.0
Classifier: Programming Language :: Python :: 3
Classifier: Programming Language :: Python :: 3.12
Requires-Dist: questionary (>=2.0.1,<3.0.0)
Requires-Dist: typer (>=0.12.0,<0.13.0)
Requires-Dist: xian-py (>=0.1.3,<0.2.0)
